README.md
setup.py
tessplan/__init__.py
tessplan/planet.py
tessplan/tessplan.py
tessplan/version.py
tessplan.egg-info/PKG-INFO
tessplan.egg-info/SOURCES.txt
tessplan.egg-info/dependency_links.txt
tessplan.egg-info/requires.txt
tessplan.egg-info/top_level.txt