Metadata-Version: 2.1
Name: tessplan
Version: 0.0.2
Summary: A tool for scheduling follow-up of transiting TESS Objects of Interest
Home-page: http://github.com/benmontet/tessplan
Author: Benjamin Montet
Author-email: bmontet@uchicago.edu
License: MIT
Platform: UNKNOWN
Classifier: Development Status :: 3 - Alpha
Classifier: Intended Audience :: Science/Research
Classifier: License :: OSI Approved :: MIT License
Classifier: Operating System :: OS Independent
Classifier: Programming Language :: Python :: 3.0
